shf/__init__.py
shf/_builtins.py
shf/main.py
shf/util.py
sams_hash_function-0.0.1.dist-info/METADATA
sams_hash_function-0.0.1.dist-info/WHEEL
sams_hash_function-0.0.1.dist-info/licenses/LICENSE
sams_hash_function-0.0.1.dist-info/RECORD
