Metadata-Version: 2.4
Name: sams_hash_function
Version: 0.0.1
Summary: Generate object hashes consistent between Python sessions
Project-URL: Homepage, https://github.com/samhaese/sams_hash_function
Project-URL: Issues, https://github.com/samhaese/sams_hash_function/issues
Author-email: Sam Haese <sam.d.haese@gmail.com>
License-Expression: MIT
License-File: LICENSE
Classifier: Operating System :: OS Independent
Classifier: Programming Language :: Python :: 3
Requires-Python: >=3.10
